basecam/__init__.py
basecam/camera.py
basecam/events.py
basecam/exceptions.py
basecam/exposure.py
basecam/mixins.py
basecam/notifier.py
basecam/utils.py
basecam/actor/__init__.py
basecam/actor/actor.py
basecam/actor/schema.json
basecam/actor/tools.py
basecam/actor/commands/__doc_parser.py
basecam/actor/commands/__init__.py
basecam/actor/commands/area.py
basecam/actor/commands/base.py
basecam/actor/commands/binning.py
basecam/actor/commands/expose.py
basecam/actor/commands/reconnect.py
basecam/actor/commands/set_default.py
basecam/actor/commands/shutter.py
basecam/actor/commands/status.py
basecam/actor/commands/temperature.py
basecam/models/__init__.py
basecam/models/builtin.py
basecam/models/card.py
basecam/models/fits.py
sdss_basecam-0.8.2.dist-info/METADATA
sdss_basecam-0.8.2.dist-info/WHEEL
sdss_basecam-0.8.2.dist-info/licenses/LICENSE.md
sdss_basecam-0.8.2.dist-info/RECORD
