Metadata-Version: 2.4
Name: sdss-basecam
Version: 0.8.2
Summary: A base library for camera wrapping and actor.
Project-URL: Homepage, https://github.com/sdss/basecam
Project-URL: Repository, https://github.com/sdss/basecam
Project-URL: Documentation, https://sdss-basecam.readthedocs.io/en/latest/
Author-email: José Sánchez-Gallego <gallegoj@uw.edu>
License-Expression: BSD-3-Clause
License-File: LICENSE.md
Requires-Python: <4,>=3.8
Requires-Dist: astropy>=5.2
Requires-Dist: sdss-clu>=2.5.3
Requires-Dist: sdsstools>=1.9.0
